bankroll/analysis/__init__.py
bankroll/analysis/analysis.py
bankroll/analysis/portfolio.py
bankroll/analysis/py.typed
bankroll/interface/__init__.py
bankroll/interface/__main__.py
bankroll/interface/bankroll.default.ini
bankroll/interface/brokers.py
bankroll/interface/configuration.py
bankroll/interface/py.typed
bankroll-0.4.1.dist-info/LICENSE
bankroll-0.4.1.dist-info/METADATA
bankroll-0.4.1.dist-info/WHEEL
bankroll-0.4.1.dist-info/entry_points.txt
bankroll-0.4.1.dist-info/top_level.txt
bankroll-0.4.1.dist-info/RECORD
