Metadata-Version: 2.1
Name: bankroll
Version: 0.4.1
Summary: Ingest portfolio and other data from multiple brokerages, and analyze it
Home-page: https://github.com/bankroll-py/bankroll
Author: Justin Spahr-Summers
Author-email: justin@jspahrsummers.com
License: MIT
Keywords: trading investing finance portfolio
Platform: UNKNOWN
Classifier: Development Status :: 3 - Alpha
Classifier: Environment :: Console
Classifier: Framework :: Jupyter
Classifier: Intended Audience :: Developers
Classifier: License :: OSI Approved :: MIT License
Classifier: Operating System :: OS Independent
Classifier: Programming Language :: Python :: 3 :: Only
Classifier: Programming Language :: Python :: 3.7
Classifier: Programming Language :: Python :: 3
Classifier: Topic :: Office/Business :: Financial :: Investment
Classifier: Typing :: Typed
Requires-Dist: bankroll-marketdata (~=0.4.0)
Requires-Dist: bankroll-model (~=0.4.0)
Requires-Dist: bankroll-broker (~=0.4.1)
Requires-Dist: numpy (~=1.17.0)
Requires-Dist: progress (~=1.5)
Requires-Dist: pyfolio (>=0.9.2)
Provides-Extra: fidelity
Requires-Dist: bankroll-broker-fidelity (~=0.4.0) ; extra == 'fidelity'
Provides-Extra: ibkr
Requires-Dist: bankroll-broker-ibkr (~=0.4.0) ; extra == 'ibkr'
Provides-Extra: schwab
Requires-Dist: bankroll-broker-schwab (~=0.4.0) ; extra == 'schwab'
Provides-Extra: vanguard
Requires-Dist: bankroll-broker-vanguard (~=0.4.0) ; extra == 'vanguard'
